pys3local/__init__.py
pys3local/_version.py
pys3local/auth.py
pys3local/cli.py
pys3local/config.py
pys3local/constants.py
pys3local/errors.py
pys3local/metadata_db.py
pys3local/models.py
pys3local/provider.py
pys3local/server.py
pys3local/xml_templates.py
pys3local/providers/__init__.py
pys3local/providers/drime.py
pys3local/providers/local.py
pys3local-0.2.1.dist-info/licenses/LICENSE
pys3local-0.2.1.dist-info/METADATA
pys3local-0.2.1.dist-info/WHEEL
pys3local-0.2.1.dist-info/entry_points.txt
pys3local-0.2.1.dist-info/top_level.txt
pys3local-0.2.1.dist-info/RECORD
