Metadata-Version: 2.4
Name: pys3local
Version: 0.2.1
Summary: Local S3 server for backup software with pluggable storage backends
Author-email: Holger Nahrstaedt <nahrstaedt@gmail.com>
License: MIT License
Project-URL: Homepage, https://github.com/holgern/pys3local
Classifier: Intended Audience :: Developers
Classifier: License :: OSI Approved :: MIT License
Classifier: Operating System :: OS Independent
Classifier: Programming Language :: Python :: 3
Classifier: Programming Language :: Python :: 3.9
Classifier: Programming Language :: Python :: 3.10
Classifier: Programming Language :: Python :: 3.11
Classifier: Programming Language :: Python :: 3.12
Classifier: Programming Language :: Python :: 3.13
Classifier: Programming Language :: Python :: 3.14
Classifier: Topic :: Software Development :: Libraries
Requires-Python: >=3.9
License-File: LICENSE
Requires-Dist: click>=8.0.0
Requires-Dist: fastapi>=0.68.0
Requires-Dist: uvicorn[standard]>=0.15.0
Requires-Dist: rich>=13.0.0
Requires-Dist: vaultconfig>=0.2.0
Requires-Dist: defusedxml>=0.7.1
Requires-Dist: python-multipart>=0.0.5
Requires-Dist: httpx
Provides-Extra: drime
Requires-Dist: pydrime>=0.7.0; extra == "drime"
Provides-Extra: dev
Requires-Dist: pytest>=7.0.0; extra == "dev"
Requires-Dist: pytest-asyncio>=0.18.0; extra == "dev"
Requires-Dist: boto3>=1.20.0; extra == "dev"
Requires-Dist: ruff>=0.1.0; extra == "dev"
Dynamic: license-file
